json_analyze.py
json_analyze-0.3.0.dist-info/LICENSE
json_analyze-0.3.0.dist-info/METADATA
json_analyze-0.3.0.dist-info/WHEEL
json_analyze-0.3.0.dist-info/entry_points.txt
json_analyze-0.3.0.dist-info/top_level.txt
json_analyze-0.3.0.dist-info/RECORD
