Metadata-Version: 2.1
Name: json-analyze
Version: 0.3.0
Summary: A small tool to check JSON data for structural and data inconsistencies.
Home-page: https://pypi.org/project/json-analyze/
Author: Tobias Ammann
Author-email: tammann@ergonomics.ch
License: MIT
Platform: UNKNOWN
Requires-Dist: jsonpath-ng
Requires-Dist: tabulate
